SimpleSerial/SimpleSerialMain.py
SimpleSerial/__init__.py
SimpleSerial/colourprint.py
SimpleSerial/communication.py
SimpleSerial/constants.py
SimpleSerial/multiRead.py
SimpleSerial-0.2.0.dist-info/METADATA
SimpleSerial-0.2.0.dist-info/WHEEL
SimpleSerial-0.2.0.dist-info/top_level.txt
SimpleSerial-0.2.0.dist-info/RECORD
