Metadata-Version: 2.1
Name: SimpleSerial
Version: 0.2.0
Summary: A tool with easy prebuilt function to communicate through PySerial
Home-page: https://github.com/Mekyle-Hemani/SimpleSerial
Author: Mekyle Hemani
Requires-Dist: pyserial
